README.rst
aco2sass.py
setup.py
aco2sass.egg-info/PKG-INFO
aco2sass.egg-info/SOURCES.txt
aco2sass.egg-info/dependency_links.txt
aco2sass.egg-info/entry_points.txt
aco2sass.egg-info/top_level.txt