Metadata-Version: 1.0
Name: aco2sass
Version: 0.1
Summary: About
